dynamocacher/__init__.py
dynamocacher/cacher.py
dynamocacher-0.0.18.dist-info/METADATA
dynamocacher-0.0.18.dist-info/WHEEL
dynamocacher-0.0.18.dist-info/top_level.txt
dynamocacher-0.0.18.dist-info/RECORD
