Metadata-Version: 2.1
Name: dynamocacher
Version: 0.0.18
Summary: storing cache using dynamodb dax
Home-page: https://github.com/thanakijwanavit/dynamocacher
Author: Nic Wanavit
Author-email: nwanavit@gmail.com
License: UNKNOWN
Platform: UNKNOWN
Classifier: Programming Language :: Python :: 3
Classifier: License :: OSI Approved :: MIT License
Classifier: Operating System :: OS Independent
Requires-Python: >=3.6
Requires-Dist: pynamodb-dax
Requires-Dist: amazon-dax-client
